llama_assistant/__init__.py
llama_assistant/agent.py
llama_assistant/config.py
llama_assistant/custom_plaintext_editor.py
llama_assistant/global_hotkey.py
llama_assistant/icons.py
llama_assistant/llama_assistant_app.py
llama_assistant/main.py
llama_assistant/model_handler.py
llama_assistant/ocr_engine.py
llama_assistant/processing_thread.py
llama_assistant/screen_capture_widget.py
llama_assistant/setting_dialog.py
llama_assistant/setting_validator.py
llama_assistant/shortcut_recorder.py
llama_assistant/speech_recognition_thread.py
llama_assistant/tray_manager.py
llama_assistant/ui_manager.py
llama_assistant/utils.py
llama_assistant/wake_word_detector.py
llama_assistant/resources/__init__.py
llama_assistant/resources/document_icon.png
llama_assistant/resources/icon.icns
llama_assistant/resources/icon.ico
llama_assistant/resources/logo.png
llama_assistant/resources/wk_hey_llama.onnx
llama_assistant-0.1.44.dist-info/licenses/LICENSE
llama_assistant-0.1.44.dist-info/METADATA
llama_assistant-0.1.44.dist-info/WHEEL
llama_assistant-0.1.44.dist-info/entry_points.txt
llama_assistant-0.1.44.dist-info/top_level.txt
llama_assistant-0.1.44.dist-info/RECORD
