Metadata-Version: 2.4
Name: llama-assistant
Version: 0.1.44
Summary: An AI assistant powered by Llama models
Author-email: Viet-Anh Nguyen <vietanh.dev@gmail.com>
License: MIT
Project-URL: Homepage, https://github.com/nrl-ai/llama-assistant
Project-URL: Bug Tracker, https://github.com/nrl-ai/llama-assistant/issues
Keywords: AI,assistant,Llama,PyQt6
Classifier: Development Status :: 3 - Alpha
Classifier: Intended Audience :: Developers
Classifier: License :: OSI Approved :: GNU General Public License v3 (GPLv3)
Classifier: Operating System :: OS Independent
Classifier: Programming Language :: Python :: 3
Classifier: Programming Language :: Python :: 3.10
Classifier: Programming Language :: Python :: 3.11
Classifier: Programming Language :: Python :: 3.12
Requires-Python: >=3.10
License-File: LICENSE
Requires-Dist: numpy==1.26.4
Requires-Dist: PyQt6==6.7.0
Requires-Dist: SpeechRecognition==3.10.4
Requires-Dist: Markdown==3.7
Requires-Dist: html2text==2024.2.26
Requires-Dist: pynput==1.7.7
Requires-Dist: llama-cpp-python==0.3.16
Requires-Dist: huggingface-hub==0.25.1
Requires-Dist: openwakeword==0.6.0
Requires-Dist: pyinstaller==6.10.0
Requires-Dist: ffmpeg-python==0.2.0
Requires-Dist: llama-index-core==0.14.9
Requires-Dist: llama-index-readers-file==0.5.5
Requires-Dist: llama-index-embeddings-huggingface==0.6.1
Requires-Dist: docx2txt==0.8
Requires-Dist: mistune==3.0.2
Requires-Dist: paddlepaddle==2.6.2
Requires-Dist: paddleocr==2.9.1
Requires-Dist: whispercpp-kit>=0.1.0
Dynamic: license-file
